.VERSION
AUTHORS.rst
CONTRIBUTING.rst
HISTORY.rst
LICENSE
MANIFEST.in
README.rst
USAGE.rst
requirements.txt
setup.cfg
setup.py
docs/Makefile
docs/authors.rst
docs/conf.py
docs/contributing.rst
docs/history.rst
docs/index.rst
docs/installation.rst
docs/modules.rst
docs/readme.rst
docs/spotifylib.rst
docs/usage.rst
requirements/development.txt
requirements/documentation.txt
requirements/testing.txt
spotifylib/.VERSION
spotifylib/__init__.py
spotifylib/_version.py
spotifylib/constants.py
spotifylib/spotifylib.py
spotifylib/spotifylibexceptions.py
spotifylib/test_spoti.py
spotifylib.egg-info/PKG-INFO
spotifylib.egg-info/SOURCES.txt
spotifylib.egg-info/dependency_links.txt
spotifylib.egg-info/not-zip-safe
spotifylib.egg-info/requires.txt
spotifylib.egg-info/top_level.txt