Metadata-Version: 1.1
Name: spotifylib
Version: 0.1.2
Summary: Spotify API Client
Home-page: https://github.com/wefner/spotifylib
Author: Oriol Fabregas
Author-email: fabregas.oriol@gmail.com
License: MIT
Keywords: spotifylib
Platform: UNKNOWN
Classifier: Development Status :: 4 - Beta
Classifier: Intended Audience :: Developers
Classifier: License :: OSI Approved :: MIT License
Classifier: Natural Language :: English
Classifier: Programming Language :: Python
